{
  "hash": "b3d60b69",
  "configHash": "ad8941eb",
  "lockfileHash": "00604c6b",
  "browserHash": "7bea6a75",
  "optimized": {
    "vue": {
      "src": "../../../../node_modules/vue/dist/vue.runtime.esm-bundler.js",
      "file": "vue.js",
      "fileHash": "b761934c",
      "needsInterop": false
    },
    "vitepress > @vue/devtools-api": {
      "src": "../../../../node_modules/@vue/devtools-api/lib/esm/index.js",
      "file": "vitepress___@vue_devtools-api.js",
      "fileHash": "825b7de6",
      "needsInterop": false
    },
    "vitepress > @vueuse/core": {
      "src": "../../../../node_modules/@vueuse/core/index.mjs",
      "file": "vitepress___@vueuse_core.js",
      "fileHash": "f2d3c15e",
      "needsInterop": false
    },
    "@theme/index": {
      "src": "../../../../node_modules/vitepress/dist/client/theme-default/index.js",
      "file": "@theme_index.js",
      "fileHash": "14bc8694",
      "needsInterop": false
    },
    "mermaid": {
      "src": "../../../../node_modules/mermaid/dist/mermaid.core.mjs",
      "file": "mermaid.js",
      "fileHash": "592ac8aa",
      "needsInterop": false
    }
  },
  "chunks": {
    "mindmap-definition-617cf8dd-WDYCHM4A": {
      "file": "mindmap-definition-617cf8dd-WDYCHM4A.js"
    },
    "sankeyDiagram-6db3d513-J2YHEUZT": {
      "file": "sankeyDiagram-6db3d513-J2YHEUZT.js"
    },
    "sequenceDiagram-465a088a-3W4JDSJQ": {
      "file": "sequenceDiagram-465a088a-3W4JDSJQ.js"
    },
    "classDiagram-48ab76fb-NMRMSZQZ": {
      "file": "classDiagram-48ab76fb-NMRMSZQZ.js"
    },
    "classDiagram-v2-8ecb0bfc-J5OBCLKZ": {
      "file": "classDiagram-v2-8ecb0bfc-J5OBCLKZ.js"
    },
    "chunk-UVGTXPKJ": {
      "file": "chunk-UVGTXPKJ.js"
    },
    "stateDiagram-b620d43f-KB5XIYGD": {
      "file": "stateDiagram-b620d43f-KB5XIYGD.js"
    },
    "stateDiagram-v2-2671c3d1-4INQSG7F": {
      "file": "stateDiagram-v2-2671c3d1-4INQSG7F.js"
    },
    "chunk-4OTW7RFS": {
      "file": "chunk-4OTW7RFS.js"
    },
    "journeyDiagram-deae3313-NGWO6IKL": {
      "file": "journeyDiagram-deae3313-NGWO6IKL.js"
    },
    "flowchart-elk-definition-e097735e-A6VCB2C2": {
      "file": "flowchart-elk-definition-e097735e-A6VCB2C2.js"
    },
    "timeline-definition-732a2638-3U4E52RK": {
      "file": "timeline-definition-732a2638-3U4E52RK.js"
    },
    "erDiagram-9cfc3649-ECQS7HXC": {
      "file": "erDiagram-9cfc3649-ECQS7HXC.js"
    },
    "gitGraphDiagram-6b463803-5QNN4PXD": {
      "file": "gitGraphDiagram-6b463803-5QNN4PXD.js"
    },
    "ganttDiagram-db6931fb-R5X52I37": {
      "file": "ganttDiagram-db6931fb-R5X52I37.js"
    },
    "infoDiagram-a336098b-U2BVWKKG": {
      "file": "infoDiagram-a336098b-U2BVWKKG.js"
    },
    "pieDiagram-a5166659-EE5KTTIM": {
      "file": "pieDiagram-a5166659-EE5KTTIM.js"
    },
    "quadrantDiagram-6c355bbc-A3WIQV2O": {
      "file": "quadrantDiagram-6c355bbc-A3WIQV2O.js"
    },
    "xychartDiagram-f746c04c-JU6I5X46": {
      "file": "xychartDiagram-f746c04c-JU6I5X46.js"
    },
    "requirementDiagram-4038b16c-7RGJ3W6Y": {
      "file": "requirementDiagram-4038b16c-7RGJ3W6Y.js"
    },
    "chunk-TA23WFY4": {
      "file": "chunk-TA23WFY4.js"
    },
    "chunk-HL7EECYQ": {
      "file": "chunk-HL7EECYQ.js"
    },
    "c4Diagram-817c8e44-KNJZG7OJ": {
      "file": "c4Diagram-817c8e44-KNJZG7OJ.js"
    },
    "chunk-Y26NEVFQ": {
      "file": "chunk-Y26NEVFQ.js"
    },
    "flowDiagram-61eb444c-KYLNDIKK": {
      "file": "flowDiagram-61eb444c-KYLNDIKK.js"
    },
    "flowDiagram-v2-2f8f667a-25UC2FAF": {
      "file": "flowDiagram-v2-2f8f667a-25UC2FAF.js"
    },
    "chunk-CZQISTAB": {
      "file": "chunk-CZQISTAB.js"
    },
    "chunk-5Y3N47RN": {
      "file": "chunk-5Y3N47RN.js"
    },
    "chunk-7RKBKKU4": {
      "file": "chunk-7RKBKKU4.js"
    },
    "chunk-2CTMAB4M": {
      "file": "chunk-2CTMAB4M.js"
    },
    "chunk-VIHQSYNR": {
      "file": "chunk-VIHQSYNR.js"
    },
    "chunk-6XTSHSIE": {
      "file": "chunk-6XTSHSIE.js"
    },
    "chunk-V3RKMIRU": {
      "file": "chunk-V3RKMIRU.js"
    },
    "chunk-3EJPJMEH": {
      "file": "chunk-3EJPJMEH.js"
    }
  }
}